MANIFEST.in
README.txt
setup.cfg
setup.py
Products/__init__.py
Products.mediaWork.egg-info/PKG-INFO
Products.mediaWork.egg-info/SOURCES.txt
Products.mediaWork.egg-info/dependency_links.txt
Products.mediaWork.egg-info/entry_points.txt
Products.mediaWork.egg-info/namespace_packages.txt
Products.mediaWork.egg-info/not-zip-safe
Products.mediaWork.egg-info/paster_plugins.txt
Products.mediaWork.egg-info/requires.txt
Products.mediaWork.egg-info/top_level.txt
Products/mediaWork/README.txt
Products/mediaWork/__init__.py
Products/mediaWork/config.py
Products/mediaWork/configure.zcml
Products/mediaWork/browser/__init__.py
Products/mediaWork/browser/configure.zcml
Products/mediaWork/content/__init__.py
Products/mediaWork/content/configure.zcml
Products/mediaWork/content/work.py
Products/mediaWork/interfaces/__init__.py
Products/mediaWork/interfaces/work.py
Products/mediaWork/portlets/__init__.py
Products/mediaWork/portlets/configure.zcml
Products/mediaWork/profiles/default/factorytool.xml
Products/mediaWork/profiles/default/metadata.xml
Products/mediaWork/profiles/default/portlets.xml
Products/mediaWork/profiles/default/rolemap.xml
Products/mediaWork/profiles/default/types.xml
Products/mediaWork/profiles/default/types/Work.xml
Products/mediaWork/tests/__init__.py
Products/mediaWork/tests/base.py
Products/mediaWork/tests/test_doctest.py