Metadata-Version: 1.0
Name: Products.mediaWork
Version: 0.2
Summary: Folderish type to store information and media about a work of art
Home-page: http://svn.plone.org/svn/collective/
Author: David Jonas
Author-email: david@intk.com
License: GPL
Keywords: type work folderish
Platform: UNKNOWN
Classifier: Framework :: Plone
Classifier: Intended Audience :: Developers
Classifier: License :: OSI Approved :: GNU General Public License (GPL)
